Metadata-Version: 2.1
Name: DotDictLib
Version: 0.1.0
Summary: A class for dot notation access to dictionaries
Author: Adarsh Dhiman
Author-email: adarshdhiman007@gmail.com
License-File: LICENSE
